{
    "search_date": "2024-11-21 11:42:57",
    "flight_date": "2024-11-29",
    "origin": "BOD",
    "destination": "PRG",
    "destination_city": "Prague",
    "url": "https://www.kayak.fr/flights/BOD-PRG/2024-11-29?sort=price_a",
    "flights": [
        {
            "departure_time": "12:50 – 07:35+1",
            "arrival_time": "12:50 – 07:35\n+1",
            "duration": "18h 45min",
            "price": "98 €",
            "origin_airport": "BOD",
            "destination_airport": "PRG",
            "is_direct": false,
            "checked_baggage": "N/A",
            "hand_baggage": "N/A",
            "layover_airport": "VCE",
            "layover_duration": "15h 25min",
            "airlines": [
                "Volotea",
                "Wizz Air Malta"
            ],
            "fare_class": "Économique",
            "flight_number": "N/A",
            "equipment_type": "N/A"
        },
        {
            "departure_time": "19:45 – 07:45+1",
            "arrival_time": "12:50 – 07:35\n+1",
            "duration": "12h 00min",
            "price": "132 €",
            "origin_airport": "BOD",
            "destination_airport": "PRG",
            "is_direct": false,
            "checked_baggage": "N/A",
            "hand_baggage": "N/A",
            "layover_airport": "VCE",
            "layover_duration": "15h 25min",
            "airlines": [
                "Volotea",
                "Wizz Air Malta"
            ],
            "fare_class": "Économique",
            "flight_number": "N/A",
            "equipment_type": "N/A"
        },
        {
            "departure_time": "19:45 – 08:10+1",
            "arrival_time": "12:50 – 07:35\n+1",
            "duration": "12h 25min",
            "price": "146 €",
            "origin_airport": "BOD",
            "destination_airport": "PRG",
            "is_direct": false,
            "checked_baggage": "N/A",
            "hand_baggage": "N/A",
            "layover_airport": "VCE",
            "layover_duration": "15h 25min",
            "airlines": [
                "Volotea",
                "Wizz Air Malta"
            ],
            "fare_class": "Économique",
            "flight_number": "N/A",
            "equipment_type": "N/A"
        },
        {
            "departure_time": "19:45 – 08:30+1",
            "arrival_time": "12:50 – 07:35\n+1",
            "duration": "12h 45min",
            "price": "151 €",
            "origin_airport": "BOD",
            "destination_airport": "PRG",
            "is_direct": false,
            "checked_baggage": "N/A",
            "hand_baggage": "N/A",
            "layover_airport": "VCE",
            "layover_duration": "15h 25min",
            "airlines": [
                "Volotea",
                "Wizz Air Malta"
            ],
            "fare_class": "N/A",
            "flight_number": "N/A",
            "equipment_type": "N/A"
        },
        {
            "departure_time": "17:40 – 07:50+1",
            "arrival_time": "N/A",
            "duration": "14h 10min",
            "price": "165 €",
            "origin_airport": "BOD",
            "destination_airport": "PRG",
            "is_direct": false,
            "checked_baggage": "N/A",
            "hand_baggage": "N/A",
            "layover_airport": "N/A",
            "layover_duration": "N/A",
            "airlines": [
                "Volotea",
                "Ryanair"
            ],
            "fare_class": "N/A",
            "flight_number": "N/A",
            "equipment_type": "N/A"
        },
        {
            "departure_time": "10:50 – 18:00",
            "arrival_time": "12:50 – 07:35\n+1",
            "duration": "7h 10min",
            "price": "166 €",
            "origin_airport": "BOD",
            "destination_airport": "PRG",
            "is_direct": false,
            "checked_baggage": "N/A",
            "hand_baggage": "N/A",
            "layover_airport": "VCE",
            "layover_duration": "15h 25min",
            "airlines": [
                "Volotea",
                "Wizz Air Malta"
            ],
            "fare_class": "N/A",
            "flight_number": "N/A",
            "equipment_type": "N/A"
        },
        {
            "departure_time": "09:45 – 20:15",
            "arrival_time": "N/A",
            "duration": "10h 30min",
            "price": "173 €",
            "origin_airport": "BOD",
            "destination_airport": "PRG",
            "is_direct": false,
            "checked_baggage": "N/A",
            "hand_baggage": "N/A",
            "layover_airport": "N/A",
            "layover_duration": "N/A",
            "airlines": [
                "Vueling"
            ],
            "fare_class": "N/A",
            "flight_number": "N/A",
            "equipment_type": "N/A"
        },
        {
            "departure_time": "07:00 – 13:05",
            "arrival_time": "N/A",
            "duration": "6h 05min",
            "price": "182 €",
            "origin_airport": "BOD",
            "destination_airport": "PRG",
            "is_direct": false,
            "checked_baggage": "N/A",
            "hand_baggage": "N/A",
            "layover_airport": "N/A",
            "layover_duration": "N/A",
            "airlines": [
                "easyJet"
            ],
            "fare_class": "N/A",
            "flight_number": "N/A",
            "equipment_type": "N/A"
        },
        {
            "departure_time": "06:10 – 21:00",
            "arrival_time": "19:45 – 07:45\n+1",
            "duration": "14h 50min",
            "price": "186 €",
            "origin_airport": "BOD",
            "destination_airport": "PRG",
            "is_direct": false,
            "checked_baggage": "N/A",
            "hand_baggage": "N/A",
            "layover_airport": "MXP",
            "layover_duration": "8h 50min",
            "airlines": [
                "easyJet",
                "Wizz Air Malta"
            ],
            "fare_class": "Standard",
            "flight_number": "N/A",
            "equipment_type": "N/A"
        },
        {
            "departure_time": "20:10 – 08:55+1",
            "arrival_time": "19:45 – 07:45\n+1",
            "duration": "12h 45min",
            "price": "190 €",
            "origin_airport": "BOD",
            "destination_airport": "PRG",
            "is_direct": false,
            "checked_baggage": "N/A",
            "hand_baggage": "N/A",
            "layover_airport": "MXP",
            "layover_duration": "8h 50min",
            "airlines": [
                "easyJet",
                "Wizz Air Malta"
            ],
            "fare_class": "Standard",
            "flight_number": "N/A",
            "equipment_type": "N/A"
        },
        {
            "departure_time": "10:50 – 22:20",
            "arrival_time": "19:45 – 07:45\n+1",
            "duration": "11h 30min",
            "price": "196 €",
            "origin_airport": "BOD",
            "destination_airport": "PRG",
            "is_direct": false,
            "checked_baggage": "N/A",
            "hand_baggage": "N/A",
            "layover_airport": "MXP",
            "layover_duration": "8h 50min",
            "airlines": [
                "easyJet",
                "Wizz Air Malta"
            ],
            "fare_class": "Standard",
            "flight_number": "N/A",
            "equipment_type": "N/A"
        },
        {
            "departure_time": "17:55 – 07:35+1",
            "arrival_time": "19:45 – 07:45\n+1",
            "duration": "13h 40min",
            "price": "196 €",
            "origin_airport": "BOD",
            "destination_airport": "PRG",
            "is_direct": false,
            "checked_baggage": "N/A",
            "hand_baggage": "N/A",
            "layover_airport": "MXP",
            "layover_duration": "8h 50min",
            "airlines": [
                "easyJet",
                "Wizz Air Malta"
            ],
            "fare_class": "N/A",
            "flight_number": "N/A",
            "equipment_type": "N/A"
        },
        {
            "departure_time": "17:40 – 07:45+1",
            "arrival_time": "N/A",
            "duration": "14h 05min",
            "price": "196 €",
            "origin_airport": "BOD",
            "destination_airport": "PRG",
            "is_direct": false,
            "checked_baggage": "N/A",
            "hand_baggage": "N/A",
            "layover_airport": "N/A",
            "layover_duration": "N/A",
            "airlines": [
                "Volotea",
                "Aeroitalia",
                "Wizz Air Malta"
            ],
            "fare_class": "N/A",
            "flight_number": "N/A",
            "equipment_type": "N/A"
        },
        {
            "departure_time": "08:30 – 20:15",
            "arrival_time": "19:45 – 07:45\n+1",
            "duration": "11h 45min",
            "price": "197 €",
            "origin_airport": "BOD",
            "destination_airport": "PRG",
            "is_direct": false,
            "checked_baggage": "N/A",
            "hand_baggage": "N/A",
            "layover_airport": "MXP",
            "layover_duration": "8h 50min",
            "airlines": [
                "easyJet",
                "Wizz Air Malta"
            ],
            "fare_class": "N/A",
            "flight_number": "N/A",
            "equipment_type": "N/A"
        },
        {
            "departure_time": "22:25 – 10:45+1",
            "arrival_time": "N/A",
            "duration": "12h 20min",
            "price": "197 €",
            "origin_airport": "BOD",
            "destination_airport": "PRG",
            "is_direct": false,
            "checked_baggage": "N/A",
            "hand_baggage": "N/A",
            "layover_airport": "N/A",
            "layover_duration": "N/A",
            "airlines": [
                "easyJet"
            ],
            "fare_class": "N/A",
            "flight_number": "N/A",
            "equipment_type": "N/A"
        }
    ]
}