{
    "search_date": "2024-11-22 06:56:06",
    "flight_date": "2024-11-23",
    "origin": "BOD",
    "destination": "EZE",
    "destination_city": "Buenos Aires",
    "url": "https://www.kayak.fr/flights/BOD-EZE/2024-11-23?sort=bestflight_a",
    "flights": [
        {
            "departure_time": "09:05 – 21:00",
            "arrival_time": "09:05 – 21:00",
            "duration": "15h 55min",
            "price": "941 €",
            "origin_airport": "BOD",
            "destination_airport": "EZE",
            "is_direct": false,
            "checked_baggage": "0",
            "hand_baggage": "1",
            "layover_airport": "MAD",
            "layover_duration": "1h 55min",
            "airlines": [
                "Iberia"
            ],
            "fare_class": "Basic"
        },
        {
            "departure_time": "09:05 – 21:00",
            "arrival_time": "09:05 – 21:00",
            "duration": "15h 55min",
            "price": "897 €",
            "origin_airport": "BOD",
            "destination_airport": "EZE",
            "is_direct": false,
            "checked_baggage": "0",
            "hand_baggage": "1",
            "layover_airport": "MAD",
            "layover_duration": "1h 55min",
            "airlines": [
                "Iberia"
            ],
            "fare_class": "Basic"
        },
        {
            "departure_time": "14:40 – 22:25+1",
            "arrival_time": "09:05 – 21:00",
            "duration": "35h 45min",
            "price": "705 €",
            "origin_airport": "BOD",
            "destination_airport": "EZE",
            "is_direct": false,
            "checked_baggage": "0",
            "hand_baggage": "1",
            "layover_airport": "ZRH",
            "layover_duration": "6h 25min",
            "airlines": [
                "Iberia"
            ],
            "fare_class": "Elight"
        },
        {
            "departure_time": "17:55 – 08:40+1",
            "arrival_time": "09:05 – 21:00",
            "duration": "18h 45min",
            "price": "1 010 €",
            "origin_airport": "BOD",
            "destination_airport": "EZE",
            "is_direct": false,
            "checked_baggage": "N/A",
            "hand_baggage": "N/A",
            "layover_airport": "MAD",
            "layover_duration": "1h 55min",
            "airlines": [
                "Iberia"
            ],
            "fare_class": "Basic"
        },
        {
            "departure_time": "17:55 – 08:40+1",
            "arrival_time": "N/A",
            "duration": "18h 45min",
            "price": "1 198 €",
            "origin_airport": "BOD",
            "destination_airport": "EZE",
            "is_direct": false,
            "checked_baggage": "N/A",
            "hand_baggage": "N/A",
            "layover_airport": "MAD",
            "layover_duration": "4h 39min",
            "airlines": [
                "Vueling",
                "Iberia"
            ],
            "fare_class": "Basic"
        },
        {
            "departure_time": "21:45 – 17:55+1",
            "arrival_time": "09:05 – 21:00",
            "duration": "24h 10min",
            "price": "1 391 €",
            "origin_airport": "BOD",
            "destination_airport": "EZE",
            "is_direct": false,
            "checked_baggage": "N/A",
            "hand_baggage": "N/A",
            "layover_airport": "MAD",
            "layover_duration": "1h 55min",
            "airlines": [
                "Iberia"
            ],
            "fare_class": "Basic"
        },
        {
            "departure_time": "14:40 – 08:40+1",
            "arrival_time": "N/A",
            "duration": "22h 00min",
            "price": "1 100 €",
            "origin_airport": "BOD",
            "destination_airport": "EZE",
            "is_direct": false,
            "checked_baggage": "N/A",
            "hand_baggage": "N/A",
            "layover_airport": "MAD",
            "layover_duration": "4h 39min",
            "airlines": [
                "SWISS",
                "Iberia"
            ],
            "fare_class": "Economy"
        },
        {
            "departure_time": "21:45 – 17:55+1",
            "arrival_time": "N/A",
            "duration": "24h 10min",
            "price": "1 599 €",
            "origin_airport": "BOD",
            "destination_airport": "EZE",
            "is_direct": false,
            "checked_baggage": "N/A",
            "hand_baggage": "N/A",
            "layover_airport": "BCN",
            "layover_duration": "9h 20min",
            "airlines": [
                "Vueling"
            ],
            "fare_class": "Optimal"
        },
        {
            "departure_time": "09:05 – 07:00+1",
            "arrival_time": "09:05 – 21:00",
            "duration": "25h 55min",
            "price": "1 148 €",
            "origin_airport": "BOD",
            "destination_airport": "EZE",
            "is_direct": false,
            "checked_baggage": "0",
            "hand_baggage": "1",
            "layover_airport": "MAD",
            "layover_duration": "1h 55min",
            "airlines": [
                "Iberia"
            ],
            "fare_class": "Basic"
        },
        {
            "departure_time": "21:45 – 17:55+1",
            "arrival_time": "09:05 – 21:00",
            "duration": "24h 10min",
            "price": "1 407 €",
            "origin_airport": "BOD",
            "destination_airport": "EZE",
            "is_direct": false,
            "checked_baggage": "0",
            "hand_baggage": "1",
            "layover_airport": "ZRH",
            "layover_duration": "3h 25min",
            "airlines": [
                "Iberia"
            ],
            "fare_class": "Economy Light"
        },
        {
            "departure_time": "06:00 – 01:00+1",
            "arrival_time": "09:05 – 21:00",
            "duration": "23h 00min",
            "price": "1 392 €",
            "origin_airport": "BOD",
            "destination_airport": "EZE",
            "is_direct": false,
            "checked_baggage": "0",
            "hand_baggage": "1",
            "layover_airport": "BCN",
            "layover_duration": "9h 20min",
            "airlines": [
                "Iberia"
            ],
            "fare_class": "Economy"
        },
        {
            "departure_time": "09:05 – 04:10+1",
            "arrival_time": "09:05 – 21:00",
            "duration": "23h 05min",
            "price": "2 002 €",
            "origin_airport": "BOD",
            "destination_airport": "EZE",
            "is_direct": false,
            "checked_baggage": "N/A",
            "hand_baggage": "N/A",
            "layover_airport": "MAD",
            "layover_duration": "5h 50min",
            "airlines": [
                "Iberia"
            ],
            "fare_class": "Basic Economy"
        },
        {
            "departure_time": "12:25 – 08:40+1",
            "arrival_time": "N/A",
            "duration": "24h 15min",
            "price": "1 127 €",
            "origin_airport": "BOD",
            "destination_airport": "EZE",
            "is_direct": false,
            "checked_baggage": "N/A",
            "hand_baggage": "N/A",
            "layover_airport": "BCN",
            "layover_duration": "9h 20min",
            "airlines": [
                "Volotea",
                "Iberia"
            ],
            "fare_class": "Economy"
        },
        {
            "departure_time": "09:05 – 01:00+1",
            "arrival_time": "09:05 – 21:00",
            "duration": "19h 55min",
            "price": "1 824 €",
            "origin_airport": "BOD",
            "destination_airport": "EZE",
            "is_direct": false,
            "checked_baggage": "N/A",
            "hand_baggage": "N/A",
            "layover_airport": "MAD",
            "layover_duration": "1h 55min",
            "airlines": [
                "Iberia"
            ],
            "fare_class": "Basic"
        },
        {
            "departure_time": "14:45 – 07:55+1",
            "arrival_time": "N/A",
            "duration": "21h 10min",
            "price": "1 650 €",
            "origin_airport": "BOD",
            "destination_airport": "EZE",
            "is_direct": false,
            "checked_baggage": "N/A",
            "hand_baggage": "N/A",
            "layover_airport": "CDG",
            "layover_duration": "4h 35min",
            "airlines": [
                "Air France",
                "Lufthansa"
            ],
            "fare_class": "Light"
        },
        {
            "departure_time": "13:20 – 07:55+1",
            "arrival_time": "N/A",
            "duration": "22h 35min",
            "price": "1 586 €",
            "origin_airport": "BOD",
            "destination_airport": "EZE",
            "is_direct": false,
            "checked_baggage": "N/A",
            "hand_baggage": "N/A",
            "layover_airport": "MAD",
            "layover_duration": "8h 30min",
            "airlines": [
                "Air France",
                "Lufthansa"
            ],
            "fare_class": "Basic"
        },
        {
            "departure_time": "06:00 – 01:00+1",
            "arrival_time": "14:40 – 22:25\n+1",
            "duration": "23h 00min",
            "price": "1 753 €",
            "origin_airport": "BOD",
            "destination_airport": "EZE",
            "is_direct": false,
            "checked_baggage": "1",
            "hand_baggage": "1",
            "layover_airport": "SXB",
            "layover_duration": "2h 50min",
            "airlines": [
                "SWISS",
                "Turkish Airlines"
            ],
            "fare_class": "Economy"
        },
        {
            "departure_time": "10:05 – 04:40+1",
            "arrival_time": "14:40 – 22:25\n+1",
            "duration": "22h 35min",
            "price": "1 759 €",
            "origin_airport": "BOD",
            "destination_airport": "EZE",
            "is_direct": false,
            "checked_baggage": "1",
            "hand_baggage": "1",
            "layover_airport": "MAD",
            "layover_duration": "0h 55min",
            "airlines": [
                "SWISS",
                "Turkish Airlines"
            ],
            "fare_class": "Basic"
        },
        {
            "departure_time": "08:50 – 07:00+1",
            "arrival_time": "14:40 – 22:25\n+1",
            "duration": "26h 10min",
            "price": "1 555 €",
            "origin_airport": "BOD",
            "destination_airport": "EZE",
            "is_direct": false,
            "checked_baggage": "1",
            "hand_baggage": "1",
            "layover_airport": "CDG",
            "layover_duration": "2h 45min",
            "airlines": [
                "SWISS",
                "Turkish Airlines"
            ],
            "fare_class": "Light"
        },
        {
            "departure_time": "10:40 – 07:55+1",
            "arrival_time": "14:40 – 22:25\n+1",
            "duration": "25h 15min",
            "price": "1 663 €",
            "origin_airport": "BOD",
            "destination_airport": "EZE",
            "is_direct": false,
            "checked_baggage": "N/A",
            "hand_baggage": "N/A",
            "layover_airport": "CDG",
            "layover_duration": "4h 10min",
            "airlines": [
                "SWISS",
                "Turkish Airlines"
            ],
            "fare_class": "Light"
        },
        {
            "departure_time": "08:50 – 07:00+1",
            "arrival_time": "N/A",
            "duration": "26h 10min",
            "price": "1 595 €",
            "origin_airport": "BOD",
            "destination_airport": "EZE",
            "is_direct": false,
            "checked_baggage": "N/A",
            "hand_baggage": "N/A",
            "layover_airport": "N/A",
            "layover_duration": "N/A",
            "airlines": [
                "easyJet",
                "KLM"
            ],
            "fare_class": "Basic"
        },
        {
            "departure_time": "09:05 – 04:10+1",
            "arrival_time": "14:40 – 22:25\n+1",
            "duration": "23h 05min",
            "price": "2 028 €",
            "origin_airport": "BOD",
            "destination_airport": "EZE",
            "is_direct": false,
            "checked_baggage": "N/A",
            "hand_baggage": "N/A",
            "layover_airport": "CDG",
            "layover_duration": "2h 20min",
            "airlines": [
                "SWISS",
                "Turkish Airlines"
            ],
            "fare_class": "Light"
        },
        {
            "departure_time": "10:05 – 07:00+1",
            "arrival_time": "N/A",
            "duration": "24h 55min",
            "price": "1 768 €",
            "origin_airport": "BOD",
            "destination_airport": "EZE",
            "is_direct": false,
            "checked_baggage": "N/A",
            "hand_baggage": "N/A",
            "layover_airport": "MRS",
            "layover_duration": "1h 50min",
            "airlines": [
                "easyJet",
                "Iberia",
                "LATAM Airlines",
                "Avianca"
            ],
            "fare_class": "Standard"
        },
        {
            "departure_time": "09:05 – 07:55+1",
            "arrival_time": "N/A",
            "duration": "26h 50min",
            "price": "1 892 €",
            "origin_airport": "BOD",
            "destination_airport": "EZE",
            "is_direct": false,
            "checked_baggage": "N/A",
            "hand_baggage": "N/A",
            "layover_airport": "GVA",
            "layover_duration": "4h 20min",
            "airlines": [
                "Iberia",
                "Lufthansa"
            ],
            "fare_class": "Standard"
        },
        {
            "departure_time": "10:05 – 07:55+1",
            "arrival_time": "17:55 – 08:40\n+1",
            "duration": "25h 50min",
            "price": "1 826 €",
            "origin_airport": "BOD",
            "destination_airport": "EZE",
            "is_direct": false,
            "checked_baggage": "0",
            "hand_baggage": "1",
            "layover_airport": "MAD",
            "layover_duration": "4h 39min",
            "airlines": [
                "Iberia"
            ],
            "fare_class": "Basic"
        }
    ]
}