{
    "search_date": "2024-11-23 07:13:58",
    "flight_date": "2025-03-05",
    "origin": "BOD",
    "destination": "CUN",
    "destination_city": "Cancún",
    "url": "https://www.kayak.fr/flights/BOD-CUN/2025-03-05?sort=bestflight_a",
    "flights": [
        {
            "departure_time": "18:00 – 12:55+1",
            "arrival_time": "18:00 – 12:55\n+1",
            "duration": "24h 55min",
            "price": "650 €",
            "origin_airport": "BOD",
            "destination_airport": "CUN",
            "is_direct": false,
            "checked_baggage": "2",
            "hand_baggage": "1",
            "layover_airport": "IST",
            "layover_duration": "2h 15min",
            "airlines": [
                "Turkish Airlines"
            ],
            "fare_class": "Promotion"
        },
        {
            "departure_time": "09:05 – 02:32+1",
            "arrival_time": "18:00 – 12:55\n+1",
            "duration": "23h 27min",
            "price": "389 €",
            "origin_airport": "BOD",
            "destination_airport": "CUN",
            "is_direct": false,
            "checked_baggage": "2",
            "hand_baggage": "1",
            "layover_airport": "MAD",
            "layover_duration": "3h 00min",
            "airlines": [
                "Turkish Airlines"
            ],
            "fare_class": "Basic"
        },
        {
            "departure_time": "09:05 – 00:53+1",
            "arrival_time": "18:00 – 12:55\n+1",
            "duration": "21h 48min",
            "price": "449 €",
            "origin_airport": "BOD",
            "destination_airport": "CUN",
            "is_direct": false,
            "checked_baggage": "2",
            "hand_baggage": "1",
            "layover_airport": "IST",
            "layover_duration": "2h 15min",
            "airlines": [
                "Turkish Airlines"
            ],
            "fare_class": "Promotion"
        },
        {
            "departure_time": "18:00 – 12:55+1",
            "arrival_time": "18:00 – 12:55\n+1",
            "duration": "24h 55min",
            "price": "640 €",
            "origin_airport": "BOD",
            "destination_airport": "CUN",
            "is_direct": false,
            "checked_baggage": "N/A",
            "hand_baggage": "N/A",
            "layover_airport": "MAD",
            "layover_duration": "3h 00min",
            "airlines": [
                "Turkish Airlines"
            ],
            "fare_class": "Basic"
        },
        {
            "departure_time": "06:00 – 18:05",
            "arrival_time": "N/A",
            "duration": "18h 05min",
            "price": "915 €",
            "origin_airport": "BOD",
            "destination_airport": "CUN",
            "is_direct": false,
            "checked_baggage": "N/A",
            "hand_baggage": "N/A",
            "layover_airport": "N/A",
            "layover_duration": "N/A",
            "airlines": [
                "Air France",
                "Air Caraïbes"
            ],
            "fare_class": "Promotion"
        },
        {
            "departure_time": "06:00 – 19:10",
            "arrival_time": "18:00 – 12:55\n+1",
            "duration": "19h 10min",
            "price": "811 €",
            "origin_airport": "BOD",
            "destination_airport": "CUN",
            "is_direct": false,
            "checked_baggage": "N/A",
            "hand_baggage": "N/A",
            "layover_airport": "IST",
            "layover_duration": "2h 15min",
            "airlines": [
                "Turkish Airlines"
            ],
            "fare_class": "Promotion"
        },
        {
            "departure_time": "06:00 – 18:15",
            "arrival_time": "N/A",
            "duration": "18h 15min",
            "price": "838 €",
            "origin_airport": "BOD",
            "destination_airport": "CUN",
            "is_direct": false,
            "checked_baggage": "N/A",
            "hand_baggage": "N/A",
            "layover_airport": "CDG-ORY",
            "layover_duration": "Escale de 5h 25min, ,[object Object]",
            "airlines": [
                "KLM",
                "Condor"
            ],
            "fare_class": "Light"
        },
        {
            "departure_time": "09:05 – 01:15+1",
            "arrival_time": "N/A",
            "duration": "22h 10min",
            "price": "1 085 €",
            "origin_airport": "BOD",
            "destination_airport": "CUN",
            "is_direct": false,
            "checked_baggage": "N/A",
            "hand_baggage": "N/A",
            "layover_airport": "CDG",
            "layover_duration": "3h 05min",
            "airlines": [
                "Iberia"
            ],
            "fare_class": "Light"
        },
        {
            "departure_time": "17:55 – 10:23+1",
            "arrival_time": "09:05 – 02:32\n+1",
            "duration": "22h 28min",
            "price": "963 €",
            "origin_airport": "BOD",
            "destination_airport": "CUN",
            "is_direct": false,
            "checked_baggage": "0",
            "hand_baggage": "0",
            "layover_airport": "AMS",
            "layover_duration": "0h 45min",
            "airlines": [
                "Iberia",
                "Aeromexico",
                "Volaris"
            ],
            "fare_class": "Light"
        },
        {
            "departure_time": "17:55 – 10:23+1",
            "arrival_time": "09:05 – 02:32\n+1",
            "duration": "22h 28min",
            "price": "981 €",
            "origin_airport": "BOD",
            "destination_airport": "CUN",
            "is_direct": false,
            "checked_baggage": "0",
            "hand_baggage": "0",
            "layover_airport": "MAD",
            "layover_duration": "2h 50min",
            "airlines": [
                "Iberia",
                "Aeromexico",
                "Volaris"
            ],
            "fare_class": "Basic"
        },
        {
            "departure_time": "17:55 – 11:45+1",
            "arrival_time": "09:05 – 02:32\n+1",
            "duration": "23h 50min",
            "price": "929 €",
            "origin_airport": "BOD",
            "destination_airport": "CUN",
            "is_direct": false,
            "checked_baggage": "0",
            "hand_baggage": "0",
            "layover_airport": "MAD",
            "layover_duration": "3h 00min",
            "airlines": [
                "Iberia",
                "Aeromexico",
                "Volaris"
            ],
            "fare_class": "Promotion"
        },
        {
            "departure_time": "06:00 – 21:05",
            "arrival_time": "09:05 – 02:32\n+1",
            "duration": "21h 05min",
            "price": "876 €",
            "origin_airport": "BOD",
            "destination_airport": "CUN",
            "is_direct": false,
            "checked_baggage": "N/A",
            "hand_baggage": "N/A",
            "layover_airport": "MAD",
            "layover_duration": "4h 25min",
            "airlines": [
                "Iberia",
                "Aeromexico",
                "Volaris"
            ],
            "fare_class": "Basic"
        },
        {
            "departure_time": "17:55 – 11:35+1",
            "arrival_time": "N/A",
            "duration": "23h 40min",
            "price": "1 342 €",
            "origin_airport": "BOD",
            "destination_airport": "CUN",
            "is_direct": false,
            "checked_baggage": "N/A",
            "hand_baggage": "N/A",
            "layover_airport": "MAD",
            "layover_duration": "4h 25min",
            "airlines": [
                "Iberia",
                "Avianca"
            ],
            "fare_class": "Basic"
        },
        {
            "departure_time": "10:40 – 19:45",
            "arrival_time": "09:05 – 02:32\n+1",
            "duration": "15h 05min",
            "price": "1 679 €",
            "origin_airport": "BOD",
            "destination_airport": "CUN",
            "is_direct": false,
            "checked_baggage": "N/A",
            "hand_baggage": "N/A",
            "layover_airport": "MAD",
            "layover_duration": "4h 35min",
            "airlines": [
                "Iberia",
                "Aeromexico",
                "Volaris"
            ],
            "fare_class": "Basic"
        },
        {
            "departure_time": "12:24 – 20:25+1",
            "arrival_time": "N/A",
            "duration": "38h 01min",
            "price": "626 €",
            "origin_airport": "BOD",
            "destination_airport": "CUN",
            "is_direct": false,
            "checked_baggage": "N/A",
            "hand_baggage": "N/A",
            "layover_airport": "CDG",
            "layover_duration": "1h 05min",
            "airlines": [
                "SNCF",
                "Air Europa"
            ],
            "fare_class": "Light"
        },
        {
            "departure_time": "20:10 – 10:23+1",
            "arrival_time": "N/A",
            "duration": "20h 13min",
            "price": "1 586 €",
            "origin_airport": "BOD",
            "destination_airport": "CUN",
            "is_direct": false,
            "checked_baggage": "N/A",
            "hand_baggage": "N/A",
            "layover_airport": "N/A",
            "layover_duration": "N/A",
            "airlines": [
                "Aeromexico"
            ],
            "fare_class": "Promotion"
        },
        {
            "departure_time": "20:10 – 09:33+1",
            "arrival_time": "09:05 – 00:53\n+1",
            "duration": "19h 23min",
            "price": "1 624 €",
            "origin_airport": "BOD",
            "destination_airport": "CUN",
            "is_direct": false,
            "checked_baggage": "0",
            "hand_baggage": "1",
            "layover_airport": "MAD",
            "layover_duration": "5h 15min",
            "airlines": [
                "Iberia",
                "Aeromexico"
            ],
            "fare_class": "Basic"
        },
        {
            "departure_time": "20:10 – 11:23+1",
            "arrival_time": "09:05 – 00:53\n+1",
            "duration": "21h 13min",
            "price": "1 569 €",
            "origin_airport": "BOD",
            "destination_airport": "CUN",
            "is_direct": false,
            "checked_baggage": "0",
            "hand_baggage": "1",
            "layover_airport": "CDG",
            "layover_duration": "2h 25min",
            "airlines": [
                "Iberia",
                "Aeromexico"
            ],
            "fare_class": "Light"
        },
        {
            "departure_time": "06:50 – 16:55",
            "arrival_time": "09:05 – 00:53\n+1",
            "duration": "16h 05min",
            "price": "1 511 €",
            "origin_airport": "BOD",
            "destination_airport": "CUN",
            "is_direct": false,
            "checked_baggage": "0",
            "hand_baggage": "1",
            "layover_airport": "PAR-ORY",
            "layover_duration": "Escale de 4h 48min, ,[object Object]",
            "airlines": [
                "Iberia",
                "Aeromexico"
            ],
            "fare_class": "Economy"
        },
        {
            "departure_time": "06:00 – 19:45",
            "arrival_time": "09:05 – 00:53\n+1",
            "duration": "19h 45min",
            "price": "1 679 €",
            "origin_airport": "BOD",
            "destination_airport": "CUN",
            "is_direct": false,
            "checked_baggage": "N/A",
            "hand_baggage": "N/A",
            "layover_airport": "CDG",
            "layover_duration": "1h 25min",
            "airlines": [
                "Iberia",
                "Aeromexico"
            ],
            "fare_class": "Basic"
        },
        {
            "departure_time": "20:10 – 13:34+1",
            "arrival_time": "N/A",
            "duration": "23h 24min",
            "price": "1 574 €",
            "origin_airport": "BOD",
            "destination_airport": "CUN",
            "is_direct": false,
            "checked_baggage": "N/A",
            "hand_baggage": "N/A",
            "layover_airport": "CDG",
            "layover_duration": "1h 25min",
            "airlines": [
                "Aeromexico"
            ],
            "fare_class": "Basic"
        },
        {
            "departure_time": "06:35 – 19:45",
            "arrival_time": "09:05 – 00:53\n+1",
            "duration": "19h 10min",
            "price": "1 701 €",
            "origin_airport": "BOD",
            "destination_airport": "CUN",
            "is_direct": false,
            "checked_baggage": "N/A",
            "hand_baggage": "N/A",
            "layover_airport": "MAD",
            "layover_duration": "3h 00min",
            "airlines": [
                "Iberia",
                "Aeromexico"
            ],
            "fare_class": "Promotion"
        },
        {
            "departure_time": "20:10 – 14:26+1",
            "arrival_time": "N/A",
            "duration": "24h 16min",
            "price": "1 574 €",
            "origin_airport": "BOD",
            "destination_airport": "CUN",
            "is_direct": false,
            "checked_baggage": "N/A",
            "hand_baggage": "N/A",
            "layover_airport": "CDG",
            "layover_duration": "1h 25min",
            "airlines": [
                "Aeromexico"
            ],
            "fare_class": "Basic"
        },
        {
            "departure_time": "06:00 – 19:45",
            "arrival_time": "N/A",
            "duration": "19h 45min",
            "price": "1 715 €",
            "origin_airport": "BOD",
            "destination_airport": "CUN",
            "is_direct": false,
            "checked_baggage": "N/A",
            "hand_baggage": "N/A",
            "layover_airport": "LGW",
            "layover_duration": "3h 20min",
            "airlines": [
                "KLM"
            ],
            "fare_class": "Standard"
        },
        {
            "departure_time": "06:35 – 19:45",
            "arrival_time": "18:00 – 12:55\n+1",
            "duration": "19h 10min",
            "price": "1 701 €",
            "origin_airport": "BOD",
            "destination_airport": "CUN",
            "is_direct": false,
            "checked_baggage": "2",
            "hand_baggage": "1",
            "layover_airport": "IST",
            "layover_duration": "2h 15min",
            "airlines": [
                "Turkish Airlines"
            ],
            "fare_class": "Promotion"
        }
    ]
}