{
    "search_date": "2024-11-21 14:43:25",
    "flight_date": "2025-02-15",
    "origin": "BOD",
    "destination": "ATH",
    "destination_city": "Athènes",
    "url": "https://www.kayak.fr/flights/BOD-ATH/2025-02-15?sort=price_a",
    "flights": [
        {
            "departure_time": "12:55 – 09:45+1",
            "arrival_time": "12:55 – 09:45\n+1",
            "duration": "19h 50min",
            "price": "106 €",
            "origin_airport": "BOD",
            "destination_airport": "ATH",
            "is_direct": false,
            "checked_baggage": "N/A",
            "hand_baggage": "N/A",
            "layover_airport": "RBA",
            "layover_duration": "7h 05min",
            "airlines": [
                "easyJet",
                "Wizz Air Malta"
            ],
            "fare_class": "Standard",
            "flight_number": "N/A",
            "equipment_type": "N/A"
        },
        {
            "departure_time": "12:30 – 01:05+1",
            "arrival_time": "12:55 – 09:45\n+1",
            "duration": "11h 35min",
            "price": "109 €",
            "origin_airport": "BOD",
            "destination_airport": "ATH",
            "is_direct": false,
            "checked_baggage": "N/A",
            "hand_baggage": "N/A",
            "layover_airport": "RBA",
            "layover_duration": "7h 05min",
            "airlines": [
                "easyJet",
                "Wizz Air Malta"
            ],
            "fare_class": "Standard",
            "flight_number": "N/A",
            "equipment_type": "N/A"
        },
        {
            "departure_time": "20:45 – 10:45+1",
            "arrival_time": "12:55 – 09:45\n+1",
            "duration": "13h 00min",
            "price": "113 €",
            "origin_airport": "BOD",
            "destination_airport": "ATH",
            "is_direct": false,
            "checked_baggage": "N/A",
            "hand_baggage": "N/A",
            "layover_airport": "RBA",
            "layover_duration": "7h 05min",
            "airlines": [
                "easyJet",
                "Wizz Air Malta"
            ],
            "fare_class": "Standard",
            "flight_number": "N/A",
            "equipment_type": "N/A"
        },
        {
            "departure_time": "06:00 – 21:45",
            "arrival_time": "12:55 – 09:45\n+1",
            "duration": "14h 45min",
            "price": "113 €",
            "origin_airport": "BOD",
            "destination_airport": "ATH",
            "is_direct": false,
            "checked_baggage": "N/A",
            "hand_baggage": "N/A",
            "layover_airport": "RBA",
            "layover_duration": "7h 05min",
            "airlines": [
                "easyJet",
                "Wizz Air Malta"
            ],
            "fare_class": "N/A",
            "flight_number": "N/A",
            "equipment_type": "N/A"
        },
        {
            "departure_time": "21:45 – 11:05+1",
            "arrival_time": "N/A",
            "duration": "12h 20min",
            "price": "114 €",
            "origin_airport": "BOD",
            "destination_airport": "ATH",
            "is_direct": false,
            "checked_baggage": "N/A",
            "hand_baggage": "N/A",
            "layover_airport": "N/A",
            "layover_duration": "N/A",
            "airlines": [
                "Vueling"
            ],
            "fare_class": "N/A",
            "flight_number": "N/A",
            "equipment_type": "N/A"
        },
        {
            "departure_time": "06:00 – 01:05+1",
            "arrival_time": "12:55 – 09:45\n+1",
            "duration": "18h 05min",
            "price": "114 €",
            "origin_airport": "BOD",
            "destination_airport": "ATH",
            "is_direct": false,
            "checked_baggage": "N/A",
            "hand_baggage": "N/A",
            "layover_airport": "RBA",
            "layover_duration": "7h 05min",
            "airlines": [
                "easyJet",
                "Wizz Air Malta"
            ],
            "fare_class": "N/A",
            "flight_number": "N/A",
            "equipment_type": "N/A"
        },
        {
            "departure_time": "17:55 – 09:45+1",
            "arrival_time": "N/A",
            "duration": "14h 50min",
            "price": "132 €",
            "origin_airport": "BOD",
            "destination_airport": "ATH",
            "is_direct": false,
            "checked_baggage": "N/A",
            "hand_baggage": "N/A",
            "layover_airport": "N/A",
            "layover_duration": "N/A",
            "airlines": [
                "Iberia",
                "Ryanair",
                "Wizz Air Malta"
            ],
            "fare_class": "N/A",
            "flight_number": "N/A",
            "equipment_type": "N/A"
        },
        {
            "departure_time": "21:45 – 11:50+1",
            "arrival_time": "N/A",
            "duration": "13h 05min",
            "price": "135 €",
            "origin_airport": "BOD",
            "destination_airport": "ATH",
            "is_direct": false,
            "checked_baggage": "N/A",
            "hand_baggage": "N/A",
            "layover_airport": "N/A",
            "layover_duration": "N/A",
            "airlines": [
                "Vueling",
                "ITA Airways"
            ],
            "fare_class": "N/A",
            "flight_number": "N/A",
            "equipment_type": "N/A"
        },
        {
            "departure_time": "12:55 – 10:00+1",
            "arrival_time": "12:30 – 01:05\n+1",
            "duration": "20h 05min",
            "price": "136 €",
            "origin_airport": "BOD",
            "destination_airport": "ATH",
            "is_direct": false,
            "checked_baggage": "N/A",
            "hand_baggage": "N/A",
            "layover_airport": "AMS",
            "layover_duration": "6h 35min",
            "airlines": [
                "KLM"
            ],
            "fare_class": "Light",
            "flight_number": "N/A",
            "equipment_type": "N/A"
        },
        {
            "departure_time": "14:45 – 02:10+1",
            "arrival_time": "12:30 – 01:05\n+1",
            "duration": "10h 25min",
            "price": "137 €",
            "origin_airport": "BOD",
            "destination_airport": "ATH",
            "is_direct": false,
            "checked_baggage": "N/A",
            "hand_baggage": "N/A",
            "layover_airport": "AMS",
            "layover_duration": "6h 35min",
            "airlines": [
                "KLM"
            ],
            "fare_class": "Light",
            "flight_number": "N/A",
            "equipment_type": "N/A"
        },
        {
            "departure_time": "14:15 – 02:10+1",
            "arrival_time": "12:30 – 01:05\n+1",
            "duration": "10h 55min",
            "price": "137 €",
            "origin_airport": "BOD",
            "destination_airport": "ATH",
            "is_direct": false,
            "checked_baggage": "N/A",
            "hand_baggage": "N/A",
            "layover_airport": "AMS",
            "layover_duration": "6h 35min",
            "airlines": [
                "KLM"
            ],
            "fare_class": "Light",
            "flight_number": "N/A",
            "equipment_type": "N/A"
        },
        {
            "departure_time": "13:20 – 02:10+1",
            "arrival_time": "12:30 – 01:05\n+1",
            "duration": "11h 50min",
            "price": "137 €",
            "origin_airport": "BOD",
            "destination_airport": "ATH",
            "is_direct": false,
            "checked_baggage": "N/A",
            "hand_baggage": "N/A",
            "layover_airport": "AMS",
            "layover_duration": "6h 35min",
            "airlines": [
                "KLM"
            ],
            "fare_class": "N/A",
            "flight_number": "N/A",
            "equipment_type": "N/A"
        },
        {
            "departure_time": "10:40 – 02:10+1",
            "arrival_time": "N/A",
            "duration": "14h 30min",
            "price": "137 €",
            "origin_airport": "BOD",
            "destination_airport": "ATH",
            "is_direct": false,
            "checked_baggage": "N/A",
            "hand_baggage": "N/A",
            "layover_airport": "N/A",
            "layover_duration": "N/A",
            "airlines": [
                "Air France"
            ],
            "fare_class": "N/A",
            "flight_number": "N/A",
            "equipment_type": "N/A"
        },
        {
            "departure_time": "08:50 – 00:40+1",
            "arrival_time": "12:30 – 01:05\n+1",
            "duration": "14h 50min",
            "price": "139 €",
            "origin_airport": "BOD",
            "destination_airport": "ATH",
            "is_direct": false,
            "checked_baggage": "N/A",
            "hand_baggage": "N/A",
            "layover_airport": "AMS",
            "layover_duration": "6h 35min",
            "airlines": [
                "KLM"
            ],
            "fare_class": "N/A",
            "flight_number": "N/A",
            "equipment_type": "N/A"
        },
        {
            "departure_time": "17:55 – 10:00+1",
            "arrival_time": "N/A",
            "duration": "15h 05min",
            "price": "141 €",
            "origin_airport": "BOD",
            "destination_airport": "ATH",
            "is_direct": false,
            "checked_baggage": "N/A",
            "hand_baggage": "N/A",
            "layover_airport": "N/A",
            "layover_duration": "N/A",
            "airlines": [
                "Iberia",
                "Ryanair",
                "easyJet"
            ],
            "fare_class": "N/A",
            "flight_number": "N/A",
            "equipment_type": "N/A"
        }
    ]
}